RibosomeProfiler/Playground.ipynb
RibosomeProfiler/RibosomeProfiler.py
RibosomeProfiler/__init__.py
RibosomeProfiler/cli.py
RibosomeProfiler/file_parser.py
RibosomeProfiler/html_report.py
RibosomeProfiler/modules.py
RibosomeProfiler/plots.py
RibosomeProfiler/qc.py
RibosomeProfiler/templates/base.html
RibosomeProfiler-0.1.2.dist-info/AUTHORS.rst
RibosomeProfiler-0.1.2.dist-info/LICENSE
RibosomeProfiler-0.1.2.dist-info/METADATA
RibosomeProfiler-0.1.2.dist-info/WHEEL
RibosomeProfiler-0.1.2.dist-info/entry_points.txt
RibosomeProfiler-0.1.2.dist-info/top_level.txt
RibosomeProfiler-0.1.2.dist-info/RECORD
