Metadata-Version: 2.1
Name: RibosomeProfiler
Version: 0.1.2
Summary: A python command-line utility for the generation of comprehensive reports on the quality of ribosome profiling (Ribo-Seq) datasets
Home-page: https://github.com/JackCurragh/RibosomeProfiler
Author: Jack Tierney
Author-email: jackcurragh@gmail.com
License: MIT license
Keywords: RibosomeProfiler
Platform: UNKNOWN
Classifier: Development Status :: 2 - Pre-Alpha
Classifier: Intended Audience :: Developers
Classifier: License :: OSI Approved :: MIT License
Classifier: Natural Language :: English
Classifier: Programming Language :: Python :: 3
Classifier: Programming Language :: Python :: 3.8
Classifier: Programming Language :: Python :: 3.9
Classifier: Programming Language :: Python :: 3.10
Requires-Python: >=3.8
License-File: LICENSE
License-File: AUTHORS.rst
